<?xml version="1.0" encoding="UTF-8"?>
<manifest xmlns="http://www.overheid.nl/2017/lvbb">
   <bestand>
      <bestandsnaam>opdracht.xml</bestandsnaam>
      <contentType>application/xml</contentType>
   </bestand>
   <bestand>
      <bestandsnaam>resultaat.xml</bestandsnaam>
      <contentType>application/xml</contentType>
   </bestand>
   <bestand>
      <bestandsnaam>manifest.xml</bestandsnaam>
      <contentType>application/xml</contentType>
   </bestand>
   <bestand>
      <bestandsnaam>ws0616AanleveringGIO_aowl_rijnland.xml</bestandsnaam>
      <contentType>application/xml</contentType>
   </bestand>
   <!-- GML -->
   <bestand>
      <bestandsnaam>ib_aangewezen_oppervlaktewaterlichamen_rijnland.gml</bestandsnaam>
      <contentType>application/gml+xml</contentType>
   </bestand>
   <!-- afbeeldingen -->
   <bestand>
      <bestandsnaam>image1.jpeg</bestandsnaam>
      <contentType>image/jpeg</contentType>
   </bestand>
   <bestand>
      <bestandsnaam>image2.jpeg</bestandsnaam>
      <contentType>image/jpeg</contentType>
   </bestand>
   <bestand>
      <bestandsnaam>image3.jpeg</bestandsnaam>
      <contentType>image/jpeg</contentType>
   </bestand>
   <bestand>
      <bestandsnaam>image4.jpeg</bestandsnaam>
      <contentType>image/jpeg</contentType>
   </bestand>
   <bestand>
      <bestandsnaam>image5.jpeg</bestandsnaam>
      <contentType>image/jpeg</contentType>
   </bestand>
   <bestand>
      <bestandsnaam>image6.jpeg</bestandsnaam>
      <contentType>image/jpeg</contentType>
   </bestand>
   <bestand>
      <bestandsnaam>image7.jpeg</bestandsnaam>
      <contentType>image/jpeg</contentType>
   </bestand>
   <!--OW-bestanden-->
   <bestand>
      <bestandsnaam>manifest-ow.xml</bestandsnaam>
      <contentType>application/xml</contentType>
   </bestand>
   <bestand>
      <bestandsnaam>owDivisie.xml</bestandsnaam>
      <contentType>application/xml</contentType>
   </bestand>
   <bestand>
      <bestandsnaam>owLocatie.xml</bestandsnaam>
      <contentType>application/xml</contentType>
   </bestand>
   <bestand>
      <bestandsnaam>owRegelingsgebied.xml</bestandsnaam>
      <contentType>application/xml</contentType>
   </bestand>
   <bestand>
      <bestandsnaam>owGebiedsaanwijzing.xml</bestandsnaam>
      <contentType>application/xml</contentType>
   </bestand>
</manifest>